LICENSE.txt
words2numsrus/__init__.py
words2numsrus/extractor.py
words2numsrus/number.py
words2numsrus-0.1.0.dist-info/LICENSE.txt
words2numsrus-0.1.0.dist-info/METADATA
words2numsrus-0.1.0.dist-info/WHEEL
words2numsrus-0.1.0.dist-info/RECORD
