Metadata-Version: 2.1
Name: words2numsrus
Version: 0.1.0
Summary: A module which can convert russian numerical words to numbers
Home-page: https://github.com/mihail8531/Word-to-Number-Russian
License: MIT
Keywords: numbers,convert,russian,numerical
Author: Max
Author-email: max.white.rabbit@gmail.com
Requires-Python: >=3.7,<4.0
Classifier: Environment :: Console
Classifier: License :: OSI Approved :: MIT License
Classifier: Operating System :: OS Independent
Classifier: Programming Language :: Python :: 3
Classifier: Programming Language :: Python :: 3.7
Classifier: Programming Language :: Python :: 3.8
Classifier: Programming Language :: Python :: 3.9
Classifier: Programming Language :: Python :: 3.10
Classifier: Programming Language :: Python :: 3.11
Classifier: Topic :: Software Development :: Libraries :: Python Modules
Requires-Dist: natasha (<1)
Requires-Dist: yargy (<0.13)
Project-URL: Repository, https://github.com/mihail8531/Word-to-Number-Russian
